agentic_kit_core/__init__.py
agentic_kit_core/base/__init__.py
agentic_kit_core/base/component.py
agentic_kit_core/base/constants.py
agentic_kit_core/base/graph.py
agentic_kit_core/base/job.py
agentic_kit_core/base/runnable.py
agentic_kit_core/base/schema.py
agentic_kit_core/base/singleton.py
agentic_kit_core/base/workflow.py
agentic_kit_core/utils/__init__.py
agentic_kit_core/utils/converter.py
agentic_kit_core/utils/parser.py
agentic_kit_core/utils/prompt.py
agentic_kit_core/utils/tools.py
agentic_kit_core-0.0.6.dist-info/METADATA
agentic_kit_core-0.0.6.dist-info/WHEEL
agentic_kit_core-0.0.6.dist-info/top_level.txt
agentic_kit_core-0.0.6.dist-info/RECORD
