Metadata-Version: 2.1
Name: agentic-kit-core
Version: 0.0.6
Summary: Agent framework based on Langchain&Langgraph
Home-page: 
Author: manson
Author-email: manson.li3307@gmail.com
Keywords: AI,LLM,Agent
Classifier: Development Status :: 4 - Beta
Classifier: Intended Audience :: Developers
Classifier: Topic :: Scientific/Engineering :: Artificial Intelligence
Classifier: Programming Language :: Python :: 3
Classifier: License :: OSI Approved :: Apache Software License
Classifier: Operating System :: OS Independent
Requires-Python: >=3.10
Requires-Dist: langgraph
Requires-Dist: langchain
Requires-Dist: langchain-core
Requires-Dist: pydantic
